muuttaa/__init__.py
muuttaa/_version.py
muuttaa/py.typed
muuttaa/types.py
muuttaa/core/__init__.py
muuttaa/core/project.py
muuttaa/core/transform.py
muuttaa-0.1.2.dist-info/METADATA
muuttaa-0.1.2.dist-info/WHEEL
muuttaa-0.1.2.dist-info/licenses/LICENSE
muuttaa-0.1.2.dist-info/RECORD
