Metadata-Version: 2.4
Name: muuttaa
Version: 0.1.2
Summary: Minimalist xarray-based climate impact framework
Project-URL: Homepage, https://github.com/brews/muuttaa
Project-URL: Documentation, https://github.com/brews/muuttaa
Project-URL: Source, https://github.com/brews/muuttaa
Project-URL: Bug Tracker, https://github.com/brews/muuttaa/issues
License-File: LICENSE
Classifier: Intended Audience :: Developers
Classifier: Intended Audience :: Science/Research
Classifier: License :: OSI Approved :: Apache Software License
Classifier: Natural Language :: English
Classifier: Operating System :: OS Independent
Classifier: Programming Language :: Python :: 3
Classifier: Topic :: Scientific/Engineering
Requires-Python: >=3.8
Requires-Dist: xarray
Provides-Extra: test
Requires-Dist: mypy; extra == 'test'
Requires-Dist: numpy; extra == 'test'
Requires-Dist: pytest; extra == 'test'
Requires-Dist: pytest-cov; extra == 'test'
Requires-Dist: ruff>=0.1.7; extra == 'test'
